{
    "dir": "ltr",
    "1": "Áttekintés",
    "2": "Források",
    "3": "Hitelek",
    "4": "Hitelegyenleg",
    "5": "Egyenleg ebben az időszakban",
    "6": "Órák ebben az időszakban",
    "7": "Erre az időszakra vonatkozóan nem áll rendelkezésre bővített felhasználási információ.",
    "8": "Az árak az alkalmazandó adókkal terheltek",
    "9": "Az árak tartalmazzák az alkalmazandó adókat",
    "10": "Órák",
    "11": "Egyensúly",
    "12": "Szerver",
    "13": "Törölt",
    "14": "mo",
    "15": "hr",
    "16": "Összesen",
    "17": "Ha több erőforrásra van szüksége, csak küldjön nekünk egy kérést, és mi örömmel módosítjuk az erőforrásokat.",
    "18": "A jelenlegi erőforrás-korlátok az alábbiakban találhatók.",
    "19": "Szerverek",
    "20": "Elérhetőség",
    "21": "Memória",
    "22": "CPU",
    "23": "Magok",
    "24": "Tárolás",
    "25": "Forgalom",
    "26": "Kiszolgálónként a következő korlátozások érvényesek:",
    "27": "Kiszolgálókat hozhat létre egy",
    "28": "Kiszolgálókat legfeljebb",
    "29": "maximális memóriaelosztás.",
    "30": "maximális elsődleges tárolóhely-kijelölés.",
    "31": "CPU-magok.",
    "32": "maximális nyilvános hálózati forgalomelosztás.",
    "33": "A fiókodhoz nem állnak rendelkezésre erőforrások.",
    "34": "Kérjük, vegye fel a kapcsolatot az ügyfélszolgálattal a limitlehetőségek megvitatása érdekében.",
    "35": "Az utolsó 50 jóváírási befizetésed itt jelenik meg. Bármilyen módosítás vagy visszatérítés nem jelenik meg.",
    "36": "Összeg",
    "37": "Hivatkozás",
    "38": "Alkalmazott",
    "39": "Nem találtak kreditpontokat.",
    "40": "Amikor kreditek kerülnek a számládra, azok itt jelennek meg."
}