{
    "dir": "ltr",
    "1": "Edit Paket Sumber Daya",
    "2": "Batal",
    "3": "Simpan",
    "4": "Paket Sumber Daya",
    "5": "Tidak ada paket sumber daya yang tersedia untuk akun Anda.",
    "6": "Silakan hubungi bagian dukungan untuk mendiskusikan opsi paket sumber daya Anda.",
    "7": "Server",
    "8": "Tersedia",
    "9": "Memori",
    "10": "CPU",
    "11": "Core",
    "12": "Penyimpanan",
    "13": "Lalu Lintas",
    "14": "Berikut ini adalah batasan per server yang berlaku:",
    "15": "Anda dapat membuat server dengan",
    "16": "Anda bisa membuat server dengan maksimum",
    "17": "alokasi memori maksimum.",
    "18": "alokasi penyimpanan primer maksimum.",
    "19": "Inti CPU.",
    "20": "alokasi lalu lintas jaringan publik maksimum.",
    "21": "Paket sumber daya berhasil diperbarui.",
    "22": "Kolom nama harus kosong atau antara 3 hingga 50 karakter."
}