{
    "dir": "ltr",
    "1": "Задача",
    "2": "Сървър",
    "3": "Заявени",
    "4": "Продължителност",
    "5": "Напредък",
    "6": "Пълна",
    "7": "Неуспешно",
    "8": "Грешки",
    "9": "Първични действия",
    "10": "Под-действия",
    "11": "Не са намерени задачи",
    "12": "Наскоро завършени задачи",
    "13": "Последни задачи",
    "14": "година",
    "15": "години",
    "16": "месец",
    "17": "месеца",
    "18": "седмица",
    "19": "седмици",
    "20": "г",
    "21": "hr",
    "22": "мин",
    "23": "сек",
    "24": "Отменен",
    "25": "По време на искането за това действие беше в ход задача по поддръжката на системата. Допълнителни заявки вероятно ще бъдат отменени, докато задачата за поддръжка на системата не приключи. Опитайте отново след пет минути.",
    "26": "Системата не успя да отговори на искането за действие. По-нататъшни опити вероятно ще бъдат отменени, докато системата реагира нормално. Опитайте отново след пет минути."
}